cograph/__init__.py
cograph-0.0.0.dist-info/LICENSE
cograph-0.0.0.dist-info/METADATA
cograph-0.0.0.dist-info/WHEEL
cograph-0.0.0.dist-info/top_level.txt
cograph-0.0.0.dist-info/RECORD
